odeintw2/__init__.py
odeintw2/_odeintw2.py
odeintw2-0.0.0.dist-info/METADATA
odeintw2-0.0.0.dist-info/WHEEL
odeintw2-0.0.0.dist-info/top_level.txt
odeintw2-0.0.0.dist-info/RECORD
